django_mailgun_mime/examples.py
django_mailgun_mime/__init__.py
django_mailgun_mime/backends.py
django_mailgun_mime-0.1.7.dist-info/WHEEL
django_mailgun_mime-0.1.7.dist-info/RECORD
django_mailgun_mime-0.1.7.dist-info/top_level.txt
django_mailgun_mime-0.1.7.dist-info/DESCRIPTION.rst
django_mailgun_mime-0.1.7.dist-info/metadata.json
django_mailgun_mime-0.1.7.dist-info/METADATA
