Metadata-Version: 1.1
Name: django-mailgun-mime
Version: 0.1.7
Summary: It is a tiny wrapper for Django that allows to send mail via Mailgun`s API.
Home-page: https://github.com/niklak/django-mailgun-mime
Author: Nikolay Gumanov
Author-email: morgenpurple@gmail.com
License: Creative Commons Attribution-ShareAlike 4.0 International
Platform: UNKNOWN
Classifier: Environment :: Web Environment
Classifier: Framework :: Django
Classifier: Intended Audience :: Developers
Classifier: Operating System :: OS Independent
Classifier: Programming Language :: Python :: 2.5
Classifier: Programming Language :: Python :: 2.6
Classifier: Programming Language :: Python :: 2.7
Classifier: Programming Language :: Python :: 3
Classifier: Programming Language :: Python :: 3.2
Classifier: Programming Language :: Python :: 3.3
Classifier: Programming Language :: Python :: 3.4
Classifier: Topic :: Internet :: WWW/HTTP
Classifier: Topic :: Internet :: WWW/HTTP :: Dynamic Content
Classifier: Topic :: Communications :: Email
